{
  "version": 2,
  "extractor": "papercropper",
  "tables": [
    {
      "url": "assets/tables/arxiv/2607.08758v1/table-001.webp",
      "caption": "",
      "page": 0,
      "index": 1,
      "width": 1724,
      "height": 377,
      "label": "Table"
    },
    {
      "url": "assets/tables/arxiv/2607.08758v1/table-002.webp",
      "caption": "",
      "page": 0,
      "index": 2,
      "width": 1731,
      "height": 880,
      "label": "Table"
    },
    {
      "url": "assets/tables/arxiv/2607.08758v1/table-003.webp",
      "caption": "",
      "page": 0,
      "index": 3,
      "width": 1402,
      "height": 463,
      "label": "Table"
    },
    {
      "url": "assets/tables/arxiv/2607.08758v1/table-004.webp",
      "caption": "",
      "page": 0,
      "index": 4,
      "width": 1728,
      "height": 795,
      "label": "Table"
    },
    {
      "url": "assets/tables/arxiv/2607.08758v1/table-005.webp",
      "caption": "",
      "page": 0,
      "index": 5,
      "width": 978,
      "height": 1347,
      "label": "Table"
    },
    {
      "url": "assets/tables/arxiv/2607.08758v1/table-006.webp",
      "caption": "",
      "page": 0,
      "index": 6,
      "width": 1377,
      "height": 484,
      "label": "Table"
    }
  ]
}